dnfal/__init__.py
dnfal/engine.py
dnfal/loggers.py
dnfal/mtypes.py
dnfal/settings.py
dnfal/vision.py
dnfal/alignment/__init__.py
dnfal/alignment/_aligner.py
dnfal/alignment/_marker.py
dnfal/alignment/_model.py
dnfal/amazon/__init__.py
dnfal/amazon/faces.py
dnfal/clustering/__init__.py
dnfal/clustering/_aro.py
dnfal/clustering/_gcg.py
dnfal/clustering/_hcg.py
dnfal/detection/__init__.py
dnfal/detection/_detector.py
dnfal/detection/_model.py
dnfal/encoding/__init__.py
dnfal/encoding/_encoder.py
dnfal/encoding/_model.py
dnfal/genderage/__init__.py
dnfal/genderage/_model.py
dnfal/genderage/_predictor.py
dnfal/persons/__init__.py
dnfal/persons/detection/__init__.py
dnfal/persons/detection/_detector.py
dnfal/persons/detection/_model/__init__.py
dnfal/persons/detection/_model/l2norm.py
dnfal/persons/detection/_model/network.py
dnfal/persons/detection/_model/resnet.py
dnfal/persons/encoding/__init__.py
dnfal/persons/encoding/_encoder.py
dnfal/persons/encoding/_model.py
dnfal-0.8.13.dist-info/LICENSE
dnfal-0.8.13.dist-info/METADATA
dnfal-0.8.13.dist-info/WHEEL
dnfal-0.8.13.dist-info/top_level.txt
dnfal-0.8.13.dist-info/RECORD
