Metadata-Version: 2.1
Name: dnfal
Version: 0.8.13
Summary: A deep learning-based library for real-time face analysis.
Home-page: https://github.com/raikel/dnfal
Author: Raikel Bordon
Author-email: raikelbl@gmail.com
License: MIT
Platform: UNKNOWN
Classifier: License :: OSI Approved :: MIT License
Classifier: Programming Language :: Python
Classifier: Programming Language :: Python :: 3
Classifier: Programming Language :: Python :: 3.6
Classifier: Programming Language :: Python :: Implementation :: CPython
Classifier: Programming Language :: Python :: Implementation :: PyPy
Requires-Python: >=3.4.0
Requires-Dist: numpy (>=1.16.0)
Requires-Dist: opencv-python (>=4.1.0.25)
Requires-Dist: torch (>=1.3.0)
Requires-Dist: torchvision (>=0.4.1)
Requires-Dist: cvtlib (>=0.8.5)
Requires-Dist: fnms (>=0.4.0)
Requires-Dist: validator-collection (>=1.3.7)
Requires-Dist: networkx (>=2.4)
Requires-Dist: boto3 (>=1.12.31)
Requires-Dist: sklearn
Requires-Dist: scipy (>=1.3.0)
